{
  "annotations": {
    "org.personaos.dag.cid": "cidv1-sha256-ac4079a163dba45b9c0157d2c2aae3c5c86d59a1cc96641d9ebed9c01feb4f32",
    "org.personaos.environment.id": "env:01KT378P0W1MVM1FY3XB76A6HR",
    "org.personaos.policy.id": "share:01KT378P12JEY04ZY6YMDVF9Z8",
    "org.personaos.project.id": "env:01KT378P0W1MVM1FY3XB76A6HR"
  },
  "artifactType": "application/vnd.personaos.artifact-bundle.v1+json",
  "config": {
    "annotations": {
      "org.opencontainers.image.title": "Implement merge sort, emit the algorithm code + a small JSON rep",
      "org.personaos.bundle.id": "bundle:01KT378P12E8Y1P95QZJSV2QQP"
    },
    "digest": "sha256:ccc90c589112fbe454094cd054bde345194b74dc6ea19bfe218d320d9b1befae",
    "mediaType": "application/vnd.personaos.artifact-bundle.config.v1+json",
    "size": 1963
  },
  "layers": [
    {
      "annotations": {
        "org.opencontainers.image.title": "manifest.json",
        "org.personaos.artifact.id": "artifact:01KT379TS1P6JCPPATSTHJMDNK",
        "org.personaos.cid": "cidv1-sha256-fdd555488b4ec67c35945eb4a20957d693dc7aa405c726f7883cc3a2c5a983ce"
      },
      "digest": "sha256:fdd555488b4ec67c35945eb4a20957d693dc7aa405c726f7883cc3a2c5a983ce",
      "mediaType": "application/vnd.personaos.json.v1",
      "size": 286
    },
    {
      "annotations": {
        "org.opencontainers.image.title": "merge_sort.py",
        "org.personaos.artifact.id": "artifact:01KT379TS2TC95KZ0NC5EEQCYY",
        "org.personaos.cid": "cidv1-sha256-5be9cad2b187dd0a887d2ce65f40248e2501fd70d7815c9fc7a5539b00f8ee45"
      },
      "digest": "sha256:5be9cad2b187dd0a887d2ce65f40248e2501fd70d7815c9fc7a5539b00f8ee45",
      "mediaType": "application/vnd.personaos.code.v1",
      "size": 579
    },
    {
      "annotations": {
        "org.opencontainers.image.title": "report.json",
        "org.personaos.artifact.id": "artifact:01KT379TS23W846KTD3EKTCMMQ",
        "org.personaos.cid": "cidv1-sha256-20c2628cc904532d6455ef3f5cfaa3351065da1b3a143c40d22a9bf45b82b13f"
      },
      "digest": "sha256:20c2628cc904532d6455ef3f5cfaa3351065da1b3a143c40d22a9bf45b82b13f",
      "mediaType": "application/vnd.personaos.json.v1",
      "size": 139
    }
  ],
  "schemaVersion": 2,
  "signature_hex": "e6e3b1701db347e5b28eac25f9a8c09ed624814dd26ab183fd79fbedbf1cc36b46166690d0ddab15f6af39ae02023bcaac049bf369371c3015bd59e0a696460b"
}