{
  "bundles": [
    "bundle:01KT37DXBKRQ8F3X5FGGSQMM01"
  ],
  "domain_context_ref": "domain:01KT37DXB7DQTJJF2A5P3V82AT",
  "project": {
    "payload": {
      "env_id": "env:01KT37DXBCKZ5C5JFN6M3CWNC5",
      "name": "Compute the first 40 prime numbers with a sieve,",
      "project_id": "env:01KT37DXBCKZ5C5JFN6M3CWNC5",
      "schema": "project/2",
      "signing_key_id": "kernel-master",
      "status": "active"
    },
    "signature_hex": "33f8697c1db777cdbcc1e9b3029ac3df4e9e1ffc4e2f292e0d9e055ed9611f1394020c7262b6927fadcdb3bc363903d250a247a36219bcdedd32c499a7aa7601",
    "signing_key_id": "kernel-master"
  },
  "schema": "project-run-export/1"
}